pycleaner/api.py
pycleaner/lib_script_split.py
pycleaner/utils.py
pycleaner/tree-sitter-python/.gitattributes
pycleaner/tree-sitter-python/.gitignore
pycleaner/tree-sitter-python/.npmignore
pycleaner/tree-sitter-python/Cargo.toml
pycleaner/tree-sitter-python/LICENSE
pycleaner/tree-sitter-python/README.md
pycleaner/tree-sitter-python/binding.gyp
pycleaner/tree-sitter-python/grammar.js
pycleaner/tree-sitter-python/package.json
pycleaner/tree-sitter-python/.git/HEAD
pycleaner/tree-sitter-python/.git/config
pycleaner/tree-sitter-python/.git/description
pycleaner/tree-sitter-python/.git/index
pycleaner/tree-sitter-python/.git/packed-refs
pycleaner/tree-sitter-python/.git/hooks/applypatch-msg.sample
pycleaner/tree-sitter-python/.git/hooks/commit-msg.sample
pycleaner/tree-sitter-python/.git/hooks/fsmonitor-watchman.sample
pycleaner/tree-sitter-python/.git/hooks/post-update.sample
pycleaner/tree-sitter-python/.git/hooks/pre-applypatch.sample
pycleaner/tree-sitter-python/.git/hooks/pre-commit.sample
pycleaner/tree-sitter-python/.git/hooks/pre-merge-commit.sample
pycleaner/tree-sitter-python/.git/hooks/pre-push.sample
pycleaner/tree-sitter-python/.git/hooks/pre-rebase.sample
pycleaner/tree-sitter-python/.git/hooks/pre-receive.sample
pycleaner/tree-sitter-python/.git/hooks/prepare-commit-msg.sample
pycleaner/tree-sitter-python/.git/hooks/push-to-checkout.sample
pycleaner/tree-sitter-python/.git/hooks/update.sample
pycleaner/tree-sitter-python/.git/info/exclude
pycleaner/tree-sitter-python/.git/logs/HEAD
pycleaner/tree-sitter-python/.git/logs/refs/heads/master
pycleaner/tree-sitter-python/.git/logs/refs/remotes/origin/HEAD
pycleaner/tree-sitter-python/.git/objects/pack/pack-5b6ef463e5cd049e58fa911f89d757214956be5e.idx
pycleaner/tree-sitter-python/.git/objects/pack/pack-5b6ef463e5cd049e58fa911f89d757214956be5e.pack
pycleaner/tree-sitter-python/.git/refs/heads/master
pycleaner/tree-sitter-python/.git/refs/remotes/origin/HEAD
pycleaner/tree-sitter-python/.github/workflows/ci.yml
cleaner_project-1.0.1.dist-info/LICENSE
cleaner_project-1.0.1.dist-info/METADATA
cleaner_project-1.0.1.dist-info/WHEEL
cleaner_project-1.0.1.dist-info/entry_points.txt
cleaner_project-1.0.1.dist-info/top_level.txt
cleaner_project-1.0.1.dist-info/RECORD
