Metadata-Version: 2.1
Name: cleaner-project
Version: 1.0.1
Summary: Partitions the project w.r.t. its core files to libraries and scripts (that is, those files that do not directly relate to the project core files). The latter can be removed with a dedicated API call and its options.
Author: lukoshkin
Author-email: lukoshkin.workspace@gmail.com
License: MIT
License-File: LICENSE
Requires-Dist: tree-sitter
